flurryflake/__init__.py
flurryflake/client.py
flurryflake/config.py
flurryflake/edge.py
flurryflake/flake.ini
flurryflake/flake.py
flurryflake/node.py
flurryflake/output.py
flurryflake/queries.py
flurryflake/snowbank.py
flurryflake/etc/flake.ini
flurryflake/filters/__init__.py
flurryflake/filters/config.py
flurryflake/filters/filter.py
flurryflake/filters/camflow/__init__.py
flurryflake/filters/camflow/w3cfilter.py
flurryflake-0.1.31.dist-info/LICENSE
flurryflake-0.1.31.dist-info/METADATA
flurryflake-0.1.31.dist-info/WHEEL
flurryflake-0.1.31.dist-info/top_level.txt
flurryflake-0.1.31.dist-info/RECORD
