Metadata-Version: 2.1
Name: flurryflake
Version: 0.1.31
Summary: Provenance graph generation for machine learning and causality analysis
Author-email: Maya Kapoor <mkapoor1@uncc.edu>
License: MIT License        
Project-URL: Homepage, https://github.com/mayakapoor/flake
Classifier: Programming Language :: Python :: 3
Classifier: License :: OSI Approved :: MIT License
Classifier: Operating System :: OS Independent
Requires-Python: >=3.7
License-File: LICENSE
